firefly_iii_treasury_id_update/__init__.py
firefly_iii_treasury_id_update/__main__.py
firefly_iii_treasury_id_update/exceptions.py
firefly_iii_treasury_id_update/firefly_iii.py
firefly_iii_treasury_id_update/main.py
firefly_iii_treasury_id_update/treasury.py
firefly_iii_treasury_id_update/utils.py
firefly_iii_treasury.id_update-0.1.0.dist-info/LICENSE
firefly_iii_treasury.id_update-0.1.0.dist-info/METADATA
firefly_iii_treasury.id_update-0.1.0.dist-info/WHEEL
firefly_iii_treasury.id_update-0.1.0.dist-info/entry_points.txt
firefly_iii_treasury.id_update-0.1.0.dist-info/top_level.txt
firefly_iii_treasury.id_update-0.1.0.dist-info/RECORD
