Metadata-Version: 2.1
Name: firefly_iii-treasury.id-update
Version: 0.1.0
Summary: Update gold price from https://treasury.id (via websocket) to firefly-iii (https://firefly-iii.org) based how much grams you have
Home-page: https://github.com/mansuf/firefly_iii-treasury.id-update
Download-URL: https://github.com/mansuf/firefly_iii-treasury.id-update/releases
Author: Rahman Yusuf
Author-email: danipart4@gmail.com
License: MIT
Keywords: firefly-iii
Classifier: Development Status :: 3 - Alpha
Classifier: Intended Audience :: Developers
Classifier: License :: OSI Approved :: MIT License
Classifier: Programming Language :: Python :: 3 :: Only
Classifier: Programming Language :: Python :: 3
Classifier: Programming Language :: Python :: 3.8
Classifier: Programming Language :: Python :: 3.9
Classifier: Programming Language :: Python :: 3.10
Classifier: Programming Language :: Python :: 3.11
Requires-Python: >=3.8
License-File: LICENSE
Requires-Dist: aiohttp
Requires-Dist: websockets
Requires-Dist: python-dotenv
